msgpackr/__init__.py
msgpackr/constants.py
msgpackr/extension.py
msgpackr/pack.py
msgpackr/unpack.py
msgpackr/unpack_debug.py
msgpackr_python-0.1.6.dist-info/LICENSE
msgpackr_python-0.1.6.dist-info/METADATA
msgpackr_python-0.1.6.dist-info/WHEEL
msgpackr_python-0.1.6.dist-info/entry_points.txt
msgpackr_python-0.1.6.dist-info/RECORD
